langful/__init__.py
langful/assetful.py
langful/config.py
langful/default.py
langful/func.py
langful/langful.py
langful/loader.py
langful/parser.py
langful-1.0.6.dist-info/licenses/LICENSE
langful-1.0.6.dist-info/METADATA
langful-1.0.6.dist-info/WHEEL
langful-1.0.6.dist-info/top_level.txt
langful-1.0.6.dist-info/RECORD
