Metadata-Version: 2.4
Name: langful
Version: 1.0.6
Summary: provides internationalization for python
Author-email: cueavyqwp <cueavy@outlook.com>
License-Expression: MIT
Project-URL: Homepage, https://github.com/cueavy/langful
Project-URL: Bug, https://github.com/cueavy/langful/issues
Project-URL: Source, https://github.com/cueavy/langful.git
Project-URL: Download, https://pypi.org/project/langful
Project-URL: Documentation, https://github.com/cueavy/langful/tree/master/docs
Keywords: i18n,json,internationalization
Classifier: Programming Language :: Python :: 3
Classifier: Programming Language :: Python :: 3.10
Classifier: Topic :: Software Development :: Internationalization
Classifier: Operating System :: OS Independent
Requires-Python: >=3.10
License-File: LICENSE
Dynamic: license-file
